{
    "action_title": "Get Vault service health",
    "action_description": "Fetches the health of the Vault service by using hvac's sys/health call.",
    "action_type": "LEGO_TYPE_VAULT",
    "action_entry_function": "vault_get_service_health",
    "action_needs_credential": true,
    "action_output_type": "ACTION_OUTPUT_TYPE_LIST",
    "action_is_check": true,
    "action_next_hop": [
      ""
    ],
    "action_next_hop_parameter_mapping": {},
    "action_supports_iteration": true,
    "action_supports_poll": true,
    "action_categories":["CATEGORY_TYPE_SECOPS","LEGO_TYPE_VAULT"]
  }