{
  "action_title": "AWS Get Generated Policy",
  "action_description": "Given a Region and the ID of a policy generation job, this Action will return the policy (once it has been completed).",
  "action_type": "LEGO_TYPE_AWS",
  "action_entry_function": "aws_get_generated_policy",
  "action_needs_credential": "true",
  "action_output_type": "ACTION_OUTPUT_TYPE_DICT",
  "action_is_check": "false",
  "action_supports_iteration": "true",
  "action_supports_poll": "true",
  "action_categories": ["CATEGORY_TYPE_CLOUDOPS", "CATEGORY_TYPE_COST_OPT","CATEGORY_TYPE_AWS","CATEGORY_TYPE_AWS_IAM"]
}