{
    "action_title": "Filter AWS EC2 Instances Without Termination and Lifetime Tag",
    "action_description": "Filter AWS EC2 Instances Without Termination and Lifetime Tag and Check of they are valid",
    "action_type": "LEGO_TYPE_AWS",
    "action_entry_function": "aws_filter_instances_without_termination_and_lifetime_tag",
    "action_needs_credential": true,
    "action_output_type": "ACTION_OUTPUT_TYPE_LIST",
    "action_supports_poll": true,
    "action_supports_iteration": true,
    "action_is_check":true,
    "action_verbs": ["filter"],
    "action_nouns": ["aws","instances","without","termination","lifetime","tag"],
    "action_categories":[ "CATEGORY_TYPE_CLOUDOPS", "CATEGORY_TYPE_DEVOPS", "CATEGORY_TYPE_COST_OPT"],
    "action_next_hop":["8744e8836d7a0aff41120620fa4d703dacff25b0dbb5c9c7b87b83783c6c9d18"],
    "action_next_hop_parameter_mapping":{}
  }